[
{
	"id": "1",
    "path":"https://raw.githubusercontent.com/ignatmsq/be/main/1.jpeg",
    "path_preview":"https://raw.githubusercontent.com/ignatmsq/be/main/1.jpeg"
},
{
	"id": "2",
    "path":"https://raw.githubusercontent.com/ignatmsq/be/main/2.jpeg",
    "path_preview":"https://raw.githubusercontent.com/ignatmsq/be/main/2.jpeg"
},
{
	"id": "3",
    "path":"https://raw.githubusercontent.com/ignatmsq/be/main/3.jpeg",
    "path_preview":"https://raw.githubusercontent.com/ignatmsq/be/main/3.jpeg"
},
{
	"id": "4",
    "path":"https://raw.githubusercontent.com/ignatmsq/be/main/4.jpeg",
    "path_preview":"https://raw.githubusercontent.com/ignatmsq/be/main/4.jpeg"
},
{
	"id": "5",
    "path":"https://raw.githubusercontent.com/ignatmsq/be/main/5.jpeg",
    "path_preview":"https://raw.githubusercontent.com/ignatmsq/be/main/5.jpeg"
},
{
	"id": "6",
    "path":"https://raw.githubusercontent.com/ignatmsq/be/main/6.jpeg",
    "path_preview":"https://raw.githubusercontent.com/ignatmsq/be/main/6.jpeg"
},
{
	"id": "7",
    "path":"https://raw.githubusercontent.com/ignatmsq/be/main/7.jpeg",
    "path_preview":"https://raw.githubusercontent.com/ignatmsq/be/main/7.jpeg"
},
{
	"id": "8",
    "path":"https://raw.githubusercontent.com/ignatmsq/be/main/8.jpeg",
    "path_preview":"https://raw.githubusercontent.com/ignatmsq/be/main/8.jpeg"
},
{
	"id": "9",
    "path":"https://raw.githubusercontent.com/ignatmsq/be/main/9.jpeg",
    "path_preview":"https://raw.githubusercontent.com/ignatmsq/be/main/9.jpeg"
},
{
	"id": "10",
    "path":"https://raw.githubusercontent.com/ignatmsq/be/main/10.jpeg",
    "path_preview":"https://raw.githubusercontent.com/ignatmsq/be/main/10.jpeg"
}

]
